{
    "content": "V mesecu aprilu bo v sklopu Zdravstvenega doma dr. Adolfa Drolca Maribor organizirana\ncepilna akcija proti klopnemu meningoencefalitisu\n.\nCepljenje se bo odvijalo 12.4.2025 od 8h do 20h (malica: od 13h do 14h) v Zdravstveni postaji Hoče.\nZa več informacij lahko občani in občanke kontaktirajo na telefonsko št. 02/620-17-83.  Cepljenje je izključno samoplačniško, cena cepljenja je 25€.",
    "metadata": {
        "source_url": "https://www.race-fram.si/objava/1063825",
        "title": "Cepilna akcija proti klopnemu meningoencefalitisu - race-fram.si",
        "scraped_at": "2025-07-07",
        "published_at": "",
        "category": "Novice",
        "data_type": "Spletna stran"
    }
}