{
    "content": "Zaključena izgradnja vodohrana Pečovnik – večja varnost oskrbe s pitno vodo\nZ veseljem sporočamo, da smo uspešno zaključili projekt izgradnje\nvodohrana Pečovnik\n, ki je ena izmed ključnih investicij Občine Rače-Fram v letu 2024 na področju izboljšanja javne vodovodne infrastrukture.\nKljučni mejniki projekta:\nPričetek del na terenu:\nmaj 2024\nZaključek del:\ndecember 2024\nPridobitev uporabnega dovoljenja:\nfebruar 2025\nGradnja je bila izvedena skladno z določili pogodbe, podpisane z izbranim izvajalcem v postopku javnega naročanja. V februarju 2025 smo pridobili\nuporabno dovoljenje\n, s čimer je bil objekt\nuradno predan v uporabo\n.\nGlavni učinki investicije:\npovečanje kapacitete za\nshranjevanje pitne vode s 100 m³ na 350 m³\n,\nizboljšano\nhidravlično delovanje\nvodovodnega sistema,\nvečja\nzanesljivost in učinkovitost\noskrbe s pitno vodo.\nVerjamemo, da ta pomembna pridobitev dolgoročno prispeva k\nvišji kakovosti življenja občanov\nin boljši pripravljenosti sistema na potrebe prihodnosti.\nNALOŽBO JE SOFINANCIRALA EVROPSKA UNIJA, REPUBLIKA SLOVENIJE IN OBČINA RAČE FRAM",
    "metadata": {
        "source_url": "https://www.race-fram.si/objava/1094414",
        "title": "Vodohrana Pečovnik - race-fram.si",
        "scraped_at": "2025-07-07",
        "published_at": "",
        "category": "Novice",
        "data_type": "Spletna stran"
    }
}